hello_world_app/__init__.py
hello_world_app/app.py
hello_world_app/static/style.css
hello_world_app/templates/index.html
cicd_betrand_mutagha_mutagha-0.1.5.dist-info/METADATA
cicd_betrand_mutagha_mutagha-0.1.5.dist-info/WHEEL
cicd_betrand_mutagha_mutagha-0.1.5.dist-info/top_level.txt
cicd_betrand_mutagha_mutagha-0.1.5.dist-info/RECORD
