Metadata-Version: 2.1
Name: cicd-betrand-mutagha-mutagha
Version: 0.1.5
Summary: A simple CI/CD Flask application
Home-page: https://github.com/Betrand1999/cicd
Author: BETRAND MUTAGHA
Author-email: mutagha2@gmail.com
License: UNKNOWN
Platform: UNKNOWN
Classifier: Development Status :: 3 - Alpha
Classifier: License :: OSI Approved :: MIT License
Classifier: Programming Language :: Python :: 3
Classifier: Programming Language :: Python :: 3.9
Classifier: Programming Language :: Python :: 3.10
Requires-Dist: flask
